odoo/addons/edi_record_metadata_oca/README.rst
odoo/addons/edi_record_metadata_oca/__init__.py
odoo/addons/edi_record_metadata_oca/__manifest__.py
odoo/addons/edi_record_metadata_oca/fields.py
odoo/addons/edi_record_metadata_oca/i18n/edi_record_metadata_oca.pot
odoo/addons/edi_record_metadata_oca/i18n/it.po
odoo/addons/edi_record_metadata_oca/models/__init__.py
odoo/addons/edi_record_metadata_oca/models/edi_exchange_consumer_mixin.py
odoo/addons/edi_record_metadata_oca/models/edi_exchange_record.py
odoo/addons/edi_record_metadata_oca/static/description/icon.png
odoo/addons/edi_record_metadata_oca/static/description/index.html
odoo/addons/edi_record_metadata_oca/tests/__init__.py
odoo/addons/edi_record_metadata_oca/tests/fake_models.py
odoo/addons/edi_record_metadata_oca/tests/test_metadata.py
odoo/addons/edi_record_metadata_oca/views/edi_exchange_record.xml
odoo_addon_edi_record_metadata_oca-18.0.1.0.1.2.dist-info/METADATA
odoo_addon_edi_record_metadata_oca-18.0.1.0.1.2.dist-info/WHEEL
odoo_addon_edi_record_metadata_oca-18.0.1.0.1.2.dist-info/top_level.txt
odoo_addon_edi_record_metadata_oca-18.0.1.0.1.2.dist-info/RECORD
